context_weave_ai_utils/__init__.py
context_weave_ai_utils/cryptic.py
context_weave_ai_utils-0.0.2.dist-info/METADATA
context_weave_ai_utils-0.0.2.dist-info/WHEEL
context_weave_ai_utils-0.0.2.dist-info/top_level.txt
context_weave_ai_utils-0.0.2.dist-info/RECORD
